LICENSE
MANIFEST.in
README.rst
pyproject.toml
setup.py
bigfile/__init__.py
bigfile/pyxbigfile.c
bigfile/pyxbigfile.pyx
bigfile/version.py
bigfile.egg-info/PKG-INFO
bigfile.egg-info/SOURCES.txt
bigfile.egg-info/dependency_links.txt
bigfile.egg-info/not-zip-safe
bigfile.egg-info/requires.txt
bigfile.egg-info/top_level.txt
bigfile/tests/__init__.py
bigfile/tests/test_bigfile.py
scripts/bigfile-convert
scripts/hdf2bigfile
src/bigfile-internal.h
src/bigfile-mpi.c
src/bigfile-mpi.h
src/bigfile-record.c
src/bigfile.c
src/bigfile.h
src/mp-mpiu.c
src/mp-mpiu.h