Metadata-Version: 2.4
Name: bigfile
Version: 0.1.52
Summary: python binding of BigFile, a peta scale IO format
Home-page: http://github.com/MP-Gadget/bigfile
Author: Yu Feng, Simeon Bird
Author-email: rainwoodman@gmail.com
License: BSD-2-Clause
License-File: LICENSE
Requires-Dist: cython
Requires-Dist: numpy
Dynamic: author
Dynamic: author-email
Dynamic: home-page
Dynamic: license
Dynamic: license-file
Dynamic: requires-dist
Dynamic: summary
